gdbundle_debuginfod/__init__.py
gdbundle_debuginfod/gdb_loader.py
gdbundle_debuginfod/lldb_loader.py
gdbundle_debuginfod/scripts/__init__.py
gdbundle_debuginfod/scripts/dbgd_plugin.py
gdbundle_debuginfod/scripts/debuginfod_gdb.py
gdbundle_debuginfod/scripts/debuginfod_lldb.py
gdbundle_debuginfod-0.4.0.dist-info/WHEEL
gdbundle_debuginfod-0.4.0.dist-info/METADATA
gdbundle_debuginfod-0.4.0.dist-info/RECORD
