Metadata-Version: 2.1
Name: gdbundle-debuginfod
Version: 0.4.0
Summary: GDB and LLDB plugins to enable older versions of GDB and LLDB to support debuginfod
License: MIT
Author: Matt Schulte
Author-email: schultetwin1@gmail.com
Requires-Python: >=3.6,<4.0
Classifier: License :: OSI Approved :: MIT License
Classifier: Programming Language :: Python :: 3
Classifier: Programming Language :: Python :: 3.6
Classifier: Programming Language :: Python :: 3.7
Classifier: Programming Language :: Python :: 3.8
Classifier: Programming Language :: Python :: 3.9
Requires-Dist: pydebuginfod (>=0.2.0,<0.3.0)
Requires-Dist: pyelftools (>=0.27,<0.28)
Requires-Dist: requests (>=2.25.1,<3.0.0)
